pddns/__init__.py
pddns/config.dist.conf
pddns/pddns.py
pddns/providers/__init__.py
pddns/providers/afraid.py
pddns/providers/cloudflare.py
pddns/providers/common.py
pddns/providers/hurricaneElectric.py
pddns/providers/strato.py
python_ddns-3.0.0.data/data/config.conf/config.dist.conf
python_ddns-3.0.0.dist-info/LICENSE
python_ddns-3.0.0.dist-info/METADATA
python_ddns-3.0.0.dist-info/WHEEL
python_ddns-3.0.0.dist-info/entry_points.txt
python_ddns-3.0.0.dist-info/top_level.txt
python_ddns-3.0.0.dist-info/RECORD
