Metadata-Version: 2.1
Name: python-ddns
Version: 3.0.0
Summary: A DDNS client that updates providers with host machine's current IP.
Home-page: https://gitlab.com/Cyb3r-Jak3/python-ddns
Author: Cyb3r Jak3
Author-email: jake@jwhite.network
License: GPL-3.0
Project-URL: Changelog, https://gitlab.com/Cyb3r-Jak3/python-ddns/-/blob/master/CHANGELOG.md
Project-URL: Issues, https://gitlab.com/Cyb3r-Jak3/python-ddns/issues
Project-URL: Source, https://gitlab.com/Cyb3r-Jak3/python-ddns
Platform: UNKNOWN
Classifier: License :: OSI Approved :: GNU General Public License v3 (GPLv3)
Classifier: Operating System :: OS Independent
Classifier: Natural Language :: English
Classifier: Programming Language :: Python :: 3 :: Only
Classifier: Topic :: System :: Installation/Setup
Classifier: Development Status :: 4 - Beta
Classifier: Intended Audience :: System Administrators
Classifier: Programming Language :: Python :: 3.6
Classifier: Programming Language :: Python :: 3.7
Classifier: Programming Language :: Python :: 3.8
Classifier: Programming Language :: Python :: 3.9
Classifier: Programming Language :: Python :: 3.10
Requires-Python: >=3.6
Requires-Dist: dnspython
Requires-Dist: requests
Requires-Dist: psutil
